ge_snowflake/__init__.py
ge_snowflake/validator.py
ge_snowflake/cli/__init__.py
ge_snowflake/cli/cli.py
ge_snowflake/core/__init__.py
ge_snowflake/utils/__init__.py
ge_snowflake_validator-1.0.0.dist-info/licenses/LICENSE
ge_snowflake_validator-1.0.0.dist-info/licenses/LICENSE.txt
ge_snowflake_validator-1.0.0.dist-info/METADATA
ge_snowflake_validator-1.0.0.dist-info/WHEEL
ge_snowflake_validator-1.0.0.dist-info/entry_points.txt
ge_snowflake_validator-1.0.0.dist-info/top_level.txt
ge_snowflake_validator-1.0.0.dist-info/RECORD
