Metadata-Version: 2.4
Name: ge-snowflake-validator
Version: 1.0.0
Summary: Dynamic data quality validation for Snowflake using Great Expectations
Author: Priya Pandey
Author-email: your.email@example.com
Requires-Python: >=3.8
License-File: LICENSE
License-File: LICENSE.txt
Requires-Dist: great-expectations>=0.18.0
Requires-Dist: snowflake-connector-python>=3.0.0
Requires-Dist: snowflake-sqlalchemy>=1.4.0
Requires-Dist: sqlalchemy<2.0.0,>=1.4.0
Requires-Dist: pyyaml>=6.0
Requires-Dist: pandas>=1.5.0
Dynamic: author
Dynamic: author-email
Dynamic: license-file
Dynamic: requires-dist
Dynamic: requires-python
Dynamic: summary
